odoo9_addon_web_widget_darkroom-9.0.1.0.1.99.dev5-py2.7-nspkg.pth
odoo9_addon_web_widget_darkroom-9.0.1.0.1.99.dev5.dist-info/DESCRIPTION.rst
odoo9_addon_web_widget_darkroom-9.0.1.0.1.99.dev5.dist-info/METADATA
odoo9_addon_web_widget_darkroom-9.0.1.0.1.99.dev5.dist-info/RECORD
odoo9_addon_web_widget_darkroom-9.0.1.0.1.99.dev5.dist-info/WHEEL
odoo9_addon_web_widget_darkroom-9.0.1.0.1.99.dev5.dist-info/metadata.json
odoo9_addon_web_widget_darkroom-9.0.1.0.1.99.dev5.dist-info/namespace_packages.txt
odoo9_addon_web_widget_darkroom-9.0.1.0.1.99.dev5.dist-info/top_level.txt
odoo_addons/web_widget_darkroom/README.rst
odoo_addons/web_widget_darkroom/__init__.py
odoo_addons/web_widget_darkroom/__openerp__.py
odoo_addons/web_widget_darkroom/i18n/ar.po
odoo_addons/web_widget_darkroom/i18n/ca.po
odoo_addons/web_widget_darkroom/i18n/de.po
odoo_addons/web_widget_darkroom/i18n/es.po
odoo_addons/web_widget_darkroom/i18n/fi.po
odoo_addons/web_widget_darkroom/i18n/fr.po
odoo_addons/web_widget_darkroom/i18n/hr.po
odoo_addons/web_widget_darkroom/i18n/it.po
odoo_addons/web_widget_darkroom/i18n/pt_BR.po
odoo_addons/web_widget_darkroom/i18n/sl.po
odoo_addons/web_widget_darkroom/i18n/tr.po
odoo_addons/web_widget_darkroom/static/description/icon.png
odoo_addons/web_widget_darkroom/static/description/modal_screenshot_1.png
odoo_addons/web_widget_darkroom/static/description/modal_screenshot_2.png
odoo_addons/web_widget_darkroom/static/lib/darkroomjs/core/darkroom.js
odoo_addons/web_widget_darkroom/static/lib/darkroomjs/core/plugin.js
odoo_addons/web_widget_darkroom/static/lib/darkroomjs/core/transformation.js
odoo_addons/web_widget_darkroom/static/lib/darkroomjs/core/utils.js
odoo_addons/web_widget_darkroom/static/src/js/widget_darkroom.js
odoo_addons/web_widget_darkroom/static/src/js/widget_darkroom_modal.js
odoo_addons/web_widget_darkroom/static/src/js/plugins/darkroom.crop.js
odoo_addons/web_widget_darkroom/static/src/js/plugins/darkroom.history.js
odoo_addons/web_widget_darkroom/static/src/js/plugins/darkroom.rotate.js
odoo_addons/web_widget_darkroom/static/src/js/plugins/darkroom.zoom.js
odoo_addons/web_widget_darkroom/static/src/less/darkroom.less
odoo_addons/web_widget_darkroom/static/src/xml/field_templates.xml
odoo_addons/web_widget_darkroom/tests/__init__.py
odoo_addons/web_widget_darkroom/tests/test_darkroom_modal.py
odoo_addons/web_widget_darkroom/views/assets.xml
odoo_addons/web_widget_darkroom/wizards/__init__.py
