Metadata-Version: 2.0
Name: odoo9-addon-web-widget-darkroom
Version: 9.0.1.0.1.99.dev5
Summary: Provides web widget for image editing and adds it to standard image widget as modal
Home-page: https://laslabs.com/
Author: LasLabs, Odoo Community Association (OCA)
Author-email: support@odoo-community.org
License: LGPL-3
Platform: UNKNOWN
Classifier: Programming Language :: Python
Classifier: Framework :: Odoo
Classifier: License :: OSI Approved :: GNU Lesser General Public License v3 (LGPLv3)
Requires-Python: ~=2.7
Requires-Dist: odoo (<9.1a,>=9.0a)
